neo_observer.py
neo_observer-1.0.1.dist-info/DESCRIPTION.rst
neo_observer-1.0.1.dist-info/METADATA
neo_observer-1.0.1.dist-info/metadata.json
neo_observer-1.0.1.dist-info/RECORD
neo_observer-1.0.1.dist-info/top_level.txt
neo_observer-1.0.1.dist-info/WHEEL
