Metadata-Version: 2.0
Name: neo-observer
Version: 1.0.1
Summary: Python module implementing the observer pattern using a centralized registry
Home-page: https://github.com/Pierre-Thibault/neo-observer
Author: Pierre Thibault
Author-email: pierre.thibault1@gmail.com
License: MIT
Keywords: messaging
Platform: UNKNOWN
Classifier: License :: OSI Approved :: MIT License
Classifier: Development Status :: 5 - Production/Stable
Classifier: Intended Audience :: Developers
Classifier: Operating System :: OS Independent
Classifier: Programming Language :: Python :: 2
